piyo/__init__.py
piyo/client.py
piyo/error.py
piyo-1.1.0.dist-info/METADATA
piyo-1.1.0.dist-info/WHEEL
piyo-1.1.0.dist-info/top_level.txt
piyo-1.1.0.dist-info/RECORD
