Metadata-Version: 2.1
Name: piyo
Version: 1.1.0
Summary: esa API v1 client library, written in python
Home-page: https://github.com/argonism/piyo
Author: k-ush
Author-email: argoooooon@gmail.com
License: MIT
Keywords: esa api client esa.io python
Classifier: License :: OSI Approved :: MIT License
Classifier: Programming Language :: Python :: 3
Classifier: Programming Language :: Python :: 3.5
Classifier: Programming Language :: Python :: 3.6
Classifier: Programming Language :: Python :: 3.7
Classifier: Programming Language :: Python :: 3.8
Classifier: Programming Language :: Python :: 3.9
Requires-Dist: requests (==2.25.1)
